{
  "_generated": "2026-04-24T19:09:12",
  "_source": "reconstruct_history.py",
  "window": 12,
  "rf_brl_atual": {
    "taxa_anual": 14.75,
    "nome": "Selic meta (CDI) — taxa atual"
  },
  "rf_brl": {
    "taxa_anual": 14.75,
    "nome": "Selic meta (CDI)"
  },
  "rf_brl_series": {
    "2021-05": 0.27,
    "2021-06": 0.31,
    "2021-07": 0.36,
    "2021-08": 0.43,
    "2021-09": 0.44,
    "2021-10": 0.49,
    "2021-11": 0.59,
    "2021-12": 0.77,
    "2022-01": 0.73,
    "2022-02": 0.76,
    "2022-03": 0.93,
    "2022-04": 0.83,
    "2022-05": 1.03,
    "2022-06": 1.02,
    "2022-07": 1.03,
    "2022-08": 1.17,
    "2022-09": 1.07,
    "2022-10": 1.02,
    "2022-11": 1.02,
    "2022-12": 1.12,
    "2023-01": 1.12,
    "2023-02": 0.92,
    "2023-03": 1.17,
    "2023-04": 0.92,
    "2023-05": 1.12,
    "2023-06": 1.07,
    "2023-07": 1.07,
    "2023-08": 1.14,
    "2023-09": 0.97,
    "2023-10": 1.0,
    "2023-11": 0.92,
    "2023-12": 0.89,
    "2024-01": 0.97,
    "2024-02": 0.8,
    "2024-03": 0.83,
    "2024-04": 0.89,
    "2024-05": 0.83,
    "2024-06": 0.79,
    "2024-07": 0.91,
    "2024-08": 0.87,
    "2024-09": 0.84,
    "2024-10": 0.93,
    "2024-11": 0.79,
    "2024-12": 0.93,
    "2025-01": 1.01,
    "2025-02": 0.99,
    "2025-03": 0.96,
    "2025-04": 1.06,
    "2025-05": 1.14,
    "2025-06": 1.1,
    "2025-07": 1.28,
    "2025-08": 1.16,
    "2025-09": 1.22,
    "2025-10": 1.28,
    "2025-11": 1.05,
    "2025-12": 1.22,
    "2026-01": 1.16,
    "2026-02": 1.0,
    "2026-03": 1.21,
    "2026-04": 0.82
  },
  "rf_usd": {
    "taxa_anual": 3.64,
    "nome": "US T-Bill 3m (≈ Fed Funds)"
  },
  "dates": [
    "2022-04",
    "2022-05",
    "2022-06",
    "2022-07",
    "2022-08",
    "2022-09",
    "2022-10",
    "2022-11",
    "2022-12",
    "2023-01",
    "2023-02",
    "2023-03",
    "2023-04",
    "2023-05",
    "2023-06",
    "2023-07",
    "2023-08",
    "2023-09",
    "2023-10",
    "2023-11",
    "2023-12",
    "2024-01",
    "2024-02",
    "2024-03",
    "2024-04",
    "2024-05",
    "2024-06",
    "2024-07",
    "2024-08",
    "2024-09",
    "2024-10",
    "2024-11",
    "2024-12",
    "2025-01",
    "2025-02",
    "2025-03",
    "2025-04",
    "2025-05",
    "2025-06",
    "2025-07",
    "2025-08",
    "2025-09",
    "2025-10",
    "2025-11",
    "2025-12",
    "2026-01",
    "2026-02",
    "2026-03",
    "2026-04"
  ],
  "sharpe_brl": [
    -0.226,
    -0.489,
    -0.298,
    -0.331,
    -0.655,
    -0.937,
    -1.284,
    -0.553,
    -0.807,
    -1.416,
    -1.227,
    -0.995,
    -0.852,
    -0.765,
    -0.518,
    -0.773,
    -0.496,
    -0.137,
    -0.74,
    -1.161,
    -0.334,
    -0.622,
    -0.21,
    0.499,
    0.625,
    1.459,
    1.769,
    1.877,
    2.01,
    2.022,
    3.312,
    3.321,
    2.648,
    2.105,
    1.422,
    0.673,
    1.329,
    1.38,
    1.101,
    1.081,
    1.083,
    0.398,
    0.376,
    0.166,
    0.298,
    0.331,
    0.475,
    0.395,
    -0.511
  ],
  "sharpe_usd": [
    -1.22,
    -1.454,
    -1.896,
    -1.365,
    -1.736,
    -1.912,
    -1.704,
    -0.86,
    -1.154,
    -0.423,
    -0.507,
    -0.5,
    -0.122,
    -0.299,
    0.518,
    0.515,
    0.481,
    0.984,
    0.378,
    0.376,
    0.896,
    0.409,
    0.769,
    1.022,
    0.818,
    1.322,
    1.05,
    0.927,
    1.322,
    1.951,
    2.176,
    2.062,
    1.036,
    1.519,
    0.948,
    0.302,
    1.205,
    1.292,
    1.41,
    1.353,
    1.459,
    0.749,
    0.892,
    0.822,
    1.004,
    1.064,
    1.258,
    1.02,
    0.674
  ],
  "sortino": [
    -0.317,
    -0.659,
    -0.418,
    -0.462,
    -0.873,
    -1.186,
    -1.494,
    -0.743,
    -1.054,
    -1.534,
    -1.378,
    -1.214,
    -1.079,
    -1.0,
    -0.694,
    -0.98,
    -0.675,
    -0.217,
    -1.013,
    -1.344,
    -0.461,
    -0.813,
    -0.289,
    0.781,
    1.002,
    2.726,
    3.937,
    4.181,
    4.485,
    4.521,
    16.329,
    17.016,
    12.549,
    6.51,
    3.454,
    1.316,
    5.463,
    5.699,
    4.475,
    4.394,
    4.4,
    0.704,
    0.666,
    0.29,
    0.521,
    0.583,
    0.842,
    0.685,
    -0.546
  ],
  "volatilidade": [
    18.323,
    18.78,
    18.03,
    18.056,
    18.333,
    18.781,
    17.433,
    18.926,
    18.754,
    15.743,
    15.273,
    13.691,
    13.215,
    12.802,
    12.924,
    12.219,
    11.54,
    10.289,
    10.845,
    9.127,
    10.22,
    9.632,
    9.78,
    9.982,
    9.724,
    9.143,
    10.875,
    10.893,
    10.738,
    10.752,
    8.55,
    8.852,
    9.059,
    9.967,
    10.996,
    11.661,
    24.455,
    24.577,
    24.216,
    24.215,
    24.186,
    29.42,
    29.413,
    29.098,
    29.167,
    29.054,
    28.728,
    29.121,
    17.93
  ],
  "max_dd": [
    -14.88,
    -18.35,
    -18.94,
    -18.94,
    -18.94,
    -21.71,
    -21.71,
    -21.71,
    -21.71,
    -21.71,
    -18.01,
    -11.56,
    -8.02,
    -8.02,
    -8.02,
    -8.02,
    -6.7,
    -6.7,
    -6.7,
    -6.7,
    -6.7,
    -6.7,
    -5.86,
    -3.93,
    -3.88,
    -3.88,
    -3.88,
    -3.88,
    -3.88,
    -3.54,
    -0.4,
    -0.4,
    -0.4,
    -1.63,
    -3.84,
    -6.71,
    -6.71,
    -6.71,
    -6.71,
    -6.71,
    -6.71,
    -14.41,
    -14.41,
    -14.41,
    -14.41,
    -14.41,
    -14.41,
    -14.41,
    -14.41
  ],
  "information_ratio": {
    "benchmark": "VWRA.L",
    "base": "USD",
    "itd": {
      "ir": 0.0769,
      "tracking_error_pct": 15.1127,
      "active_return_anual_pct": 1.1625,
      "n_meses": 60
    },
    "rolling_36m": {
      "dates": [
        "2024-04",
        "2024-05",
        "2024-06",
        "2024-07",
        "2024-08",
        "2024-09",
        "2024-10",
        "2024-11",
        "2024-12",
        "2025-01",
        "2025-02",
        "2025-03",
        "2025-04",
        "2025-05",
        "2025-06",
        "2025-07",
        "2025-08",
        "2025-09",
        "2025-10",
        "2025-11",
        "2025-12",
        "2026-01",
        "2026-02",
        "2026-03",
        "2026-04"
      ],
      "values": [
        -0.7877,
        -0.7794,
        -0.8563,
        -0.6419,
        -0.6772,
        -0.6555,
        -0.6397,
        -0.5447,
        -0.5891,
        -0.574,
        -0.6272,
        -0.2816,
        0.4906,
        0.4493,
        0.4676,
        0.4831,
        0.5153,
        0.1684,
        0.1362,
        0.111,
        0.1175,
        0.1498,
        0.1941,
        0.2394,
        0.2432
      ],
      "nota": "N=25 pontos — baixa robustez estatística"
    }
  }
}